setup.py
s7svrsim/__init__.py
s7svrsim/hints.py
s7svrsim-0.2.0.dist-info/METADATA
s7svrsim-0.2.0.dist-info/WHEEL
s7svrsim-0.2.0.dist-info/top_level.txt
s7svrsim-0.2.0.dist-info/RECORD
