Metadata-Version: 2.4
Name: s7svrsim
Version: 0.2.0
Summary: Add your description here
Requires-Python: >=3.11
